pika-stubs/__init__.pyi
pika-stubs/amqp_object.pyi
pika-stubs/callback.pyi
pika-stubs/channel.pyi
pika-stubs/compat.pyi
pika-stubs/connection.pyi
pika-stubs/credentials.pyi
pika-stubs/exceptions.pyi
pika-stubs/exchange_type.pyi
pika-stubs/frame.pyi
pika-stubs/spec.pyi
pika-stubs/adapters/__init__.pyi
pika-stubs/adapters/asyncio_connection.pyi
pika-stubs/adapters/base_connection.pyi
pika-stubs/adapters/blocking_connection.pyi
pika-stubs/adapters/select_connection.pyi
pika-stubs/adapters/tornado_connection.pyi
pika-stubs/adapters/twisted_connection.pyi
pika-stubs/adapters/utils/__init__.pyi
pika-stubs/adapters/utils/connection_workflow.pyi
pika-stubs/adapters/utils/io_services_utils.pyi
pika-stubs/adapters/utils/nbio_interface.pyi
pika-stubs/adapters/utils/selector_ioloop_adapter.pyi
types_pika-1.2.0b1.dist-info/LICENSE
types_pika-1.2.0b1.dist-info/METADATA
types_pika-1.2.0b1.dist-info/WHEEL
types_pika-1.2.0b1.dist-info/top_level.txt
types_pika-1.2.0b1.dist-info/RECORD
